presto/__init__.py
trino/__init__.py
trino/auth.py
trino/client.py
trino/constants.py
trino/dbapi.py
trino/exceptions.py
trino/logging.py
trino/transaction.py
presto_client-0.303.0.dist-info/LICENSE
presto_client-0.303.0.dist-info/METADATA
presto_client-0.303.0.dist-info/WHEEL
presto_client-0.303.0.dist-info/top_level.txt
presto_client-0.303.0.dist-info/RECORD
